proxymloxy/__init__.py
proxymloxy/configfile.jinja
proxymloxy/proxymloxy.py
proxymloxy-1.3.0.dist-info/entry_points.txt
proxymloxy-1.3.0.dist-info/LICENSE
proxymloxy-1.3.0.dist-info/WHEEL
proxymloxy-1.3.0.dist-info/METADATA
proxymloxy-1.3.0.dist-info/RECORD
