Metadata-Version: 2.1
Name: proxymloxy
Version: 1.3.0
Summary: Reverse Proxy Manager with simple YAML configuration
Keywords: reverse-proxy,proxmox
Author-email: Johannes Krattenmacher <proxymloxy@dev.krateng.ch>
Requires-Python: >=3.6
Classifier: Programming Language :: Python :: 3
Classifier: License :: OSI Approved :: GNU General Public License v3 (GPLv3)
Classifier: Operating System :: OS Independent
Requires-Dist: jinja2
Requires-Dist: ipaddress
Requires-Dist: PyYAML
Requires-Dist: doreah
Project-URL: repository, https://github.com/krateng/proxymloxy
